.DS_Store
speedboot/__init__.py
speedboot/speedboot.py
speedboot-0.0.23.dist-info/LICENSE
speedboot-0.0.23.dist-info/METADATA
speedboot-0.0.23.dist-info/WHEEL
speedboot-0.0.23.dist-info/top_level.txt
speedboot-0.0.23.dist-info/RECORD
