Metadata-Version: 2.1
Name: speedboot
Version: 0.0.23
Summary: Bootstrap library for vector-valued statistics with BCa confidence intervals.
Home-page: UNKNOWN
Author: François Grolleau
Author-email: <francois.grolleau@aphp.fr>
License: UNKNOWN
Keywords: bootstrap,confidence intervals,statistics,inference,parallel
Platform: UNKNOWN
Classifier: License :: OSI Approved :: MIT License
Classifier: Development Status :: 1 - Planning
Classifier: Intended Audience :: Science/Research
Classifier: Programming Language :: Python :: 3
Classifier: Operating System :: Unix
Classifier: Operating System :: MacOS :: MacOS X
Classifier: Operating System :: Microsoft :: Windows
Requires-Dist: joblib
Requires-Dist: tqdm
